LICENSE
ip_object_browser/__init__.py
ip_object_browser/binding.py
ip_object_browser/browse.py
ip_object_browser/nodes.py
ip_object_browser/search.py
ip_object_browser/widgets.py
ip_object_browser-0.3.0.dist-info/LICENSE
ip_object_browser-0.3.0.dist-info/WHEEL
ip_object_browser-0.3.0.dist-info/METADATA
ip_object_browser-0.3.0.dist-info/RECORD
