Metadata-Version: 2.1
Name: ip-object-browser
Version: 0.3.0
Summary: Browse big nested data structures in ipython with keyboard
Home-page: https://github.com/roee30/ip_object_browser
License: MIT
Keywords: urwid,json,tui,ipython
Author: Roee Nizan
Author-email: roeen30@gmail.com
Requires-Python: >=3.7,<4.0
Classifier: Environment :: Console
Classifier: License :: OSI Approved :: MIT License
Classifier: Operating System :: OS Independent
Classifier: Programming Language :: Python :: 3
Classifier: Programming Language :: Python :: 3.7
Classifier: Programming Language :: Python :: 3.8
Classifier: Programming Language :: Python :: 3.9
Requires-Dist: boltons (>=20.2.1,<21.0.0)
Requires-Dist: ipython (>=7.21.0,<8.0.0)
Requires-Dist: urwid (>=2.1.2,<3.0.0)
Project-URL: Repository, https://github.com/roee30/ip_object_browser
